griffine/__init__.py
griffine/__version__.py
griffine/exceptions.py
griffine/grid.py
griffine/py.typed
griffine/types.py
griffine-0.1.0.dist-info/METADATA
griffine-0.1.0.dist-info/WHEEL
griffine-0.1.0.dist-info/licenses/LICENSE
griffine-0.1.0.dist-info/RECORD
