Metadata-Version: 2.4
Name: griffine
Version: 0.1.0
Summary: Utilities for working with raster grids defined by affine transforms
Project-URL: Repository, https://github.com/jkeifer/griffine
Author-email: Jarrett Keifer <jkeifer0@gmail.com>
License: MIT
License-File: LICENSE
Requires-Python: >=3.11
Requires-Dist: affine>=2.4.0
Requires-Dist: pygeoif>=1.5.1
